{
  "schemaVersion": "reef-species.v1",
  "species": [
    {
      "id": "branching-coral",
      "commonName": "Branching coral",
      "scientificName": "Acropora cervicornis",
      "guild": "coral",
      "trophicLevel": 1.2,
      "thermalOptimum": 27.2,
      "thermalTolerance": 2.2,
      "phOptimum": 8.08,
      "phTolerance": 0.18,
      "growthRate": 0.036,
      "mortalityRate": 0.012,
      "startingPopulation": 58,
      "color": "#ff8f7e",
      "soundSignature": "crackle",
      "notes": "Fast-growing framework coral that bleaches quickly during heat stress."
    },
    {
      "id": "massive-coral",
      "commonName": "Massive star coral",
      "scientificName": "Orbicella faveolata",
      "guild": "coral",
      "trophicLevel": 1.2,
      "thermalOptimum": 27.8,
      "thermalTolerance": 2.8,
      "phOptimum": 8.04,
      "phTolerance": 0.2,
      "growthRate": 0.018,
      "mortalityRate": 0.007,
      "startingPopulation": 42,
      "color": "#f4b45f",
      "soundSignature": "crackle",
      "notes": "Slower reef builder with more thermal inertia than branching corals."
    },
    {
      "id": "table-coral",
      "commonName": "Table coral",
      "scientificName": "Acropora hyacinthus",
      "guild": "coral",
      "trophicLevel": 1.2,
      "thermalOptimum": 27.1,
      "thermalTolerance": 2,
      "phOptimum": 8.1,
      "phTolerance": 0.16,
      "growthRate": 0.031,
      "mortalityRate": 0.011,
      "startingPopulation": 35,
      "color": "#f36c66",
      "soundSignature": "crackle",
      "notes": "Can dominate shallow reef structure but is vulnerable to bleaching."
    },
    {
      "id": "turf-algae",
      "commonName": "Turf algae",
      "scientificName": "Mixed algal turf assemblage",
      "guild": "algae",
      "trophicLevel": 1,
      "thermalOptimum": 29,
      "thermalTolerance": 4.4,
      "phOptimum": 8,
      "phTolerance": 0.34,
      "growthRate": 0.083,
      "mortalityRate": 0.006,
      "startingPopulation": 32,
      "color": "#55b56a",
      "soundSignature": "shimmer",
      "notes": "Rapid colonizer that expands when herbivory drops or coral cover opens."
    },
    {
      "id": "macroalgae",
      "commonName": "Brown macroalgae",
      "scientificName": "Sargassum polycystum",
      "guild": "algae",
      "trophicLevel": 1,
      "thermalOptimum": 28.8,
      "thermalTolerance": 4,
      "phOptimum": 7.94,
      "phTolerance": 0.32,
      "growthRate": 0.068,
      "mortalityRate": 0.005,
      "startingPopulation": 24,
      "color": "#7da453",
      "soundSignature": "drone",
      "notes": "Can shade and smother coral when grazing pressure weakens."
    },
    {
      "id": "coralline-algae",
      "commonName": "Crustose coralline algae",
      "scientificName": "Porolithon onkodes",
      "guild": "algae",
      "trophicLevel": 1,
      "thermalOptimum": 27.5,
      "thermalTolerance": 2.6,
      "phOptimum": 8.08,
      "phTolerance": 0.15,
      "growthRate": 0.022,
      "mortalityRate": 0.008,
      "startingPopulation": 26,
      "color": "#c55d9d",
      "soundSignature": "shimmer",
      "notes": "Calcifying algae that helps coral settlement but suffers under low pH."
    },
    {
      "id": "parrotfish",
      "commonName": "Stoplight parrotfish",
      "scientificName": "Sparisoma viride",
      "guild": "herbivore",
      "trophicLevel": 2,
      "thermalOptimum": 27.6,
      "thermalTolerance": 3,
      "phOptimum": 8.02,
      "phTolerance": 0.28,
      "growthRate": 0.028,
      "mortalityRate": 0.014,
      "startingPopulation": 30,
      "color": "#27c0a6",
      "soundSignature": "graze",
      "notes": "Key grazer that keeps algae from overtaking coral space."
    },
    {
      "id": "surgeonfish",
      "commonName": "Blue tang surgeonfish",
      "scientificName": "Acanthurus coeruleus",
      "guild": "herbivore",
      "trophicLevel": 2,
      "thermalOptimum": 27.8,
      "thermalTolerance": 3.2,
      "phOptimum": 8.01,
      "phTolerance": 0.26,
      "growthRate": 0.032,
      "mortalityRate": 0.015,
      "startingPopulation": 34,
      "color": "#2670d8",
      "soundSignature": "graze",
      "notes": "Mobile browser that clips algal growth across exposed reef patches."
    },
    {
      "id": "damselfish",
      "commonName": "Dusky damselfish",
      "scientificName": "Stegastes adustus",
      "guild": "planktivore",
      "trophicLevel": 2.4,
      "thermalOptimum": 28.1,
      "thermalTolerance": 3.1,
      "phOptimum": 8,
      "phTolerance": 0.25,
      "growthRate": 0.034,
      "mortalityRate": 0.018,
      "startingPopulation": 28,
      "color": "#5867d8",
      "soundSignature": "pulse",
      "notes": "Territorial fish that adds reef sound but can farm algae locally."
    },
    {
      "id": "cleaner-wrasse",
      "commonName": "Cleaner wrasse",
      "scientificName": "Labroides dimidiatus",
      "guild": "planktivore",
      "trophicLevel": 2.6,
      "thermalOptimum": 27.4,
      "thermalTolerance": 2.7,
      "phOptimum": 8.04,
      "phTolerance": 0.23,
      "growthRate": 0.025,
      "mortalityRate": 0.016,
      "startingPopulation": 18,
      "color": "#8fd2ff",
      "soundSignature": "pulse",
      "notes": "Small fish that supports community resilience through cleaning behavior."
    },
    {
      "id": "grouper",
      "commonName": "Nassau grouper",
      "scientificName": "Epinephelus striatus",
      "guild": "predator",
      "trophicLevel": 4,
      "thermalOptimum": 27.3,
      "thermalTolerance": 2.6,
      "phOptimum": 8.03,
      "phTolerance": 0.24,
      "growthRate": 0.013,
      "mortalityRate": 0.013,
      "startingPopulation": 8,
      "color": "#d88c48",
      "soundSignature": "drone",
      "notes": "Predator whose decline can destabilize smaller fish communities."
    },
    {
      "id": "urchin",
      "commonName": "Long-spined sea urchin",
      "scientificName": "Diadema antillarum",
      "guild": "grazer",
      "trophicLevel": 2,
      "thermalOptimum": 27.2,
      "thermalTolerance": 2.5,
      "phOptimum": 8.06,
      "phTolerance": 0.18,
      "growthRate": 0.021,
      "mortalityRate": 0.018,
      "startingPopulation": 14,
      "color": "#2d2138",
      "soundSignature": "graze",
      "notes": "Benthic grazer that can compensate when herbivorous fish are scarce."
    }
  ]
}
